ucsmsdk_samples/__init__.py
ucsmsdk_samples/ucsmsdk_samples.py
ucsmsdk_samples/admin/__init__.py
ucsmsdk_samples/admin/autocore_exporter.py
ucsmsdk_samples/admin/backup_policy.py
ucsmsdk_samples/admin/callhome.py
ucsmsdk_samples/admin/dns.py
ucsmsdk_samples/admin/domain.py
ucsmsdk_samples/admin/keyring.py
ucsmsdk_samples/admin/ldap.py
ucsmsdk_samples/admin/locale.py
ucsmsdk_samples/admin/radius.py
ucsmsdk_samples/admin/role.py
ucsmsdk_samples/admin/snmp.py
ucsmsdk_samples/admin/syslog.py
ucsmsdk_samples/admin/tacacsplus.py
ucsmsdk_samples/admin/tftp_exporter.py
ucsmsdk_samples/admin/timezone.py
ucsmsdk_samples/admin/user.py
ucsmsdk_samples/firmware/__init__.py
ucsmsdk_samples/firmware/hostfirmwarepack.py
ucsmsdk_samples/firmware/ucsfirmware.py
ucsmsdk_samples/network/__init__.py
ucsmsdk_samples/network/ip_pools.py
ucsmsdk_samples/network/lan_conn_policy.py
ucsmsdk_samples/network/mac_pools.py
ucsmsdk_samples/network/mcast_policy.py
ucsmsdk_samples/network/nwctrl_policy.py
ucsmsdk_samples/network/qos.py
ucsmsdk_samples/network/server_port.py
ucsmsdk_samples/network/vlan.py
ucsmsdk_samples/network/vnic.py
ucsmsdk_samples/reports/__init__.py
ucsmsdk_samples/reports/serials.py
ucsmsdk_samples/server/__init__.py
ucsmsdk_samples/server/adapter_policy.py
ucsmsdk_samples/server/bios.py
ucsmsdk_samples/server/bmc.py
ucsmsdk_samples/server/boot_policy.py
ucsmsdk_samples/server/hfp_policy.py
ucsmsdk_samples/server/local_disk_policy.py
ucsmsdk_samples/server/maintenance_policy.py
ucsmsdk_samples/server/org.py
ucsmsdk_samples/server/power_control_policy.py
ucsmsdk_samples/server/scrub_policy.py
ucsmsdk_samples/server/sdcard.py
ucsmsdk_samples/server/serverdeployment.py
ucsmsdk_samples/server/service_profile.py
ucsmsdk_samples/server/sol_policy.py
ucsmsdk_samples/server/vmedia.py
ucsmsdk_samples-0.9.0.0.dist-info/DESCRIPTION.rst
ucsmsdk_samples-0.9.0.0.dist-info/METADATA
ucsmsdk_samples-0.9.0.0.dist-info/RECORD
ucsmsdk_samples-0.9.0.0.dist-info/WHEEL
ucsmsdk_samples-0.9.0.0.dist-info/metadata.json
ucsmsdk_samples-0.9.0.0.dist-info/top_level.txt
