Metadata-Version: 2.0
Name: ucsmsdk-samples
Version: 0.9.0.0
Summary: samples for ucsmsdk
Home-page: https://github.com/ciscoucs/ucsmsdk_samples
Author: Vikrant Balyan
Author-email: vvb@cisco.com
License: http://www.apache.org/licenses/LICENSE-2.0
Keywords: ucsmsdk_samples
Platform: UNKNOWN
Classifier: Development Status :: 4 - Beta
Classifier: Intended Audience :: Developers
Classifier: License :: OSI Approved :: Apache Software License
Classifier: Natural Language :: English
Classifier: Programming Language :: Python :: 2
Classifier: Programming Language :: Python :: 2.6
Classifier: Programming Language :: Python :: 2.7
Requires-Dist: ucsmsdk
Provides-Extra: docs
Requires-Dist: sphinx (<1.3); extra == 'docs'
Requires-Dist: sphinx-rtd-theme; extra == 'docs'
Requires-Dist: sphinxcontrib-napoleon; extra == 'docs'
